PhaseDiagram/__init__.py
PhaseDiagram/phaseplane.py
PhaseDiagram/phasesphere.py
PhaseDiagram/plot.py
PhaseDiagram-0.3.3.dist-info/LICENSE
PhaseDiagram-0.3.3.dist-info/METADATA
PhaseDiagram-0.3.3.dist-info/WHEEL
PhaseDiagram-0.3.3.dist-info/top_level.txt
PhaseDiagram-0.3.3.dist-info/RECORD
