Metadata-Version: 2.1
Name: PhaseDiagram
Version: 0.3.3
Summary: Adaptive-grid phase diagram calculation and plotting routines
Home-page: https://github.com/Spuriosity1/PhaseDiagram
Author: Spuriosity1
License: GPLv3+
Project-URL: Bug Reports, https://github.com/Spuriosity1/PhaseDiagram/issues
Platform: UNKNOWN
Classifier: Development Status :: 3 - Alpha
Classifier: Programming Language :: Python :: 3
Classifier: License :: OSI Approved :: GNU General Public License v3 or later (GPLv3+)
Classifier: Operating System :: OS Independent
Classifier: Intended Audience :: Science/Research
Classifier: Topic :: Scientific/Engineering :: Physics
License-File: LICENSE
Requires-Dist: numpy
Requires-Dist: scipy
Requires-Dist: matplotlib
